yandex_images_crawler/__init__.py
yandex_images_crawler/count_checker.py
yandex_images_crawler/download.py
yandex_images_crawler/image_loader.py
yandex_images_crawler/yandex_crawler.py
yandex_images_crawler-1.3.1.dist-info/LICENSE
yandex_images_crawler-1.3.1.dist-info/METADATA
yandex_images_crawler-1.3.1.dist-info/WHEEL
yandex_images_crawler-1.3.1.dist-info/entry_points.txt
yandex_images_crawler-1.3.1.dist-info/top_level.txt
yandex_images_crawler-1.3.1.dist-info/RECORD
