Metadata-Version: 2.1
Name: yandex-images-crawler
Version: 1.3.1
Summary: Crawler/parser for Yandex Images
Home-page: https://github.com/suborofu/yandex-images-crawler
Author: suborofu
Author-email: alexfromsuvorov@gmail.com
Classifier: License :: OSI Approved :: MIT License
Classifier: Programming Language :: Python
Classifier: Programming Language :: Python :: 3
Classifier: Programming Language :: Python :: 3.7
Classifier: Programming Language :: Python :: 3.8
Classifier: Programming Language :: Python :: 3.9
Classifier: Programming Language :: Python :: 3.10
Classifier: Programming Language :: Python :: 3.11
Classifier: Programming Language :: Python :: 3.12
Classifier: Topic :: Internet :: WWW/HTTP
Classifier: Topic :: Software Development :: Libraries :: Python Modules
Classifier: Topic :: Scientific/Engineering :: Image Processing
Classifier: Topic :: Utilities
Requires-Python: >=3.7
License-File: LICENSE
Requires-Dist: numpy>=1.25.0
Requires-Dist: selenium>=4.15.0
Requires-Dist: Pillow>=9.0.0
Requires-Dist: requests>=2.30.0
